LICENSE
MANIFEST.in
README.md
requirements.txt
setup.cfg
setup.py
Geolet/__init__.py
Geolet.egg-info/PKG-INFO
Geolet.egg-info/SOURCES.txt
Geolet.egg-info/dependency_links.txt
Geolet.egg-info/requires.txt
Geolet.egg-info/top_level.txt
Geolet/classifier/__init__.py
Geolet/classifier/geoletclassifier.py
Geolet/distancers/DistancerInterface.py
Geolet/distancers/Euclidean.py
Geolet/distancers/InterpolatedRouteDistance.py
Geolet/distancers/__init__.py
Geolet/normalizers/FirstPoint.py
Geolet/normalizers/NormalizerInterface.py
Geolet/normalizers/__init__.py
Geolet/normalizers/normalizer_utils.py
Geolet/partitioners/Geohash.py
Geolet/partitioners/PartitionerInterface.py
Geolet/partitioners/__init__.py
Geolet/selectors/Random.py
Geolet/selectors/RandomInformationGain.py
Geolet/selectors/SelectorInterface.py
Geolet/selectors/__init__.py
Geolet/utils/__init__.py