Metadata-Version: 2.1
Name: Geolet
Version: 0.0.1
Summary: Package description
Home-page: https://github.com/cri98li/Geolet
Author: cri98li
Author-email: cri98li@gmail.com
License: BSD-Clause-2
Keywords: keyword1 keyword2 keyword3
Classifier: Development Status :: 4 - Beta
Classifier: Intended Audience :: Developers
Classifier: Topic :: Software Development :: Build Tools
Classifier: License :: OSI Approved :: BSD License
Classifier: Operating System :: POSIX :: Other
Classifier: Operating System :: MacOS
Classifier: Programming Language :: Python
Classifier: Programming Language :: Python :: 3
Provides-Extra: flag
License-File: LICENSE
